{
    "urnid": "db60044923000305",
    "img_path": "./images/db60044923000305.jpg",
    "raw_ocr_text": "AE lo.\nae f\u00f6re konstitusjonelt ansvar for Regjeringen (Rt.\n; ' 1918 s. 646)\",\nI Bt. 1915 5.753-761 er det en artikkel av\noverrettssakf\u00f6rer Sverre Helliksen: \"Kan en konsti-\n\u00c5 tuert embedsmand avs\u00e6ttes uten dom ?\". artikkelen\ninneholder bl.a. historiske opplysninger om konstl-\ntusjonsformens benyttelse. S\u00e5ledes var regjerings-\n| advokatembetet bare besatt ved konstitusjon i \u00e5rene\nVA Ine PE ag fra 1825-1859. Og administrasjonen anvendte konsti-\nnome VE tusjonsformen ved opprettelsen av nye embeter, hvor\nV\u00c6R 05 fo \u00c5 det alts\u00e5 \u00e5penbart ikke kunne bli tale om noen\n(fru p\u00e5 a med Hettud midlertidig ledighet, fordi det aldri hadde eksi-\nBuan aulttet ) stert noen annen fast innehaver hvis forhold dannet\nen konstitusjonsgrunn. Meningen med disse stil-\nlingers besettelse var da ogs\u00e5 at den konstituerte\nskulle bli i embetet, men med \u00e5\u00e5n bevisste forut-\nsetning fra administrasjonens side at den skulle\nkunne foreta omreguleringer av embetet, helt ned-\nlegge det og endog oppsi eller avsette innehaveren\nuten \u00e5 nedlegge embetet. Videre opplyser Helliksen\nmens Stortinget 1 nyere tid\nat mkxfensridirsidkesteiodyitte hadde vist sin vel\u00bb\ni vilje overfor konstitusjonsformen ved uttrykselig \u00e5\ngi mw anvisning derp\u00e5 (eks. stortingsdokument nr.70-\n1911 8. 1), nader tidligere gjentatte ganger mis-\nbilliget den uegentlige konstitusjon. Protokoll-\nkomiteen i 1839 uttal\u00f8e at slik konstitusjon w\u00e5 an-\nSes som en virkelig fast ansettelse, slik at \"deslige\nfor \u00f8n Mands hele Enbedstid bestemte Konstitutioner\nikke skj\u00f6nnes \u00e5 v\u00e6re forfatningsmessige\" og \" saavel \u00c5\n' med Hensyn til Varighed av Posternes Besiddelse som \u00c5\n\u00c5dgangen til Pension har v\u00e6ret betragtet 1 lige ;\n",
    "corrected_ocr_text": "AE lo.\nae f\u00f6re konstitusjonelt ansvar for Regjeringen (Rt.\n; ' 1918 s 646)\",\nI Bt. 1915 5.753-761 er det en artikkel av\noverrettssakf\u00f8rer Sverre Helliksen: Kan en konsti-\ng tvert embedsmand avsettes uten dom ?\". artikkelen\ninneholder bla historiske opplysninger om konstl-\ntusjonsformens benyttelse. S\u00e5ledes var regjerings-\n|advokatembetet bare besatt ved konstitusjon i \u00e5rene\nVA Ine PE ag fra 1825-1859. Og administrasjonen anvendte konsti-\nnome VE aksjonsformen ved opprettelsen av nye embeter, hvor\nV\u00c6R 05 fo \u00c5 det alts\u00e5 \u00e5penbart ikke kunne bli tale om noen\nfru p\u00e5 a med Hestad midlertidig ledighet, fordi det aldri hadde eksi-\nBuan sluttet ) stert noen annen fast innehaver hvis forhold dannet\nen konstitusjonsgrunn. Meningen med disse stil-\nlingers besettelse var da ogs\u00e5 at den konstituerte\nskulle bli i embetet, men med l\u00e5n bevisste forut-\nsetning fra administrasjonens side at den skulle\nkunne foreta omreguleringer av embetet, helt ned-\nlegge det og endog oppsi eller avsette innehaveren\nuten \u00e5 nedlegge embetet. Videre opplyser Helliksen\nmens Stortinget 1 nyere tid\nat mkxfensridirsidkesteiodyitte hadde vist sin vel\ni vilje overfor konstitusjonsreformen ved uttrykkelig \u00e5\ngi mw anvisning derp\u00e5 (eks. stortingsdokument nr.70-\n1911 8. 1), nader tidligere gjentatte ganger mis-\nbilliget den uegentlige konstitusjon. protokoll-\nkomiteen i 1839 uttalte at slik konstitusjon p\u00e5 an-\nses som en virkelig fast ansettelse, slik at deslige\nfor \u00f8n Mands hele embedstid bestemte Konstitutionen\nikke skj\u00f8nnes \u00e5 v\u00e6re forfatningsmessige og \" saavel \u00c5\n' med Hensyn til Varighet av Postens Besiddelse som \u00c5\nadgangen til Pension har v\u00e6ret betragtet 1 lige ;\n",
    "tokens": [
        "AE",
        "lo",
        ".",
        "\n",
        "ae",
        "f\u00f6re",
        "konstitusjonelt",
        "ansvar",
        "for",
        "Regjeringen",
        "(",
        "Rt",
        ".",
        "\n",
        ";",
        "'",
        "1918",
        "s",
        "646",
        ")",
        "\"",
        ",",
        "\n",
        "I",
        "Bt",
        ".",
        "1915",
        "5.753-761",
        "er",
        "det",
        "en",
        "artikkel",
        "av",
        "\n",
        "overrettssakf\u00f8rer",
        "Sverre",
        "Helliksen",
        ":",
        "Kan",
        "en",
        "konsti-",
        "\n",
        "g",
        "tvert",
        "embedsmand",
        "avsettes",
        "uten",
        "dom",
        "?\"",
        ".",
        "artikkelen",
        "\n",
        "inneholder",
        "bla",
        "historiske",
        "opplysninger",
        "om",
        "konstl-",
        "\n",
        "tusjonsformens",
        "benyttelse",
        ".",
        "S\u00e5ledes",
        "var",
        "regjerings-",
        "\n",
        "|advokatembetet",
        "bare",
        "besatt",
        "ved",
        "konstitusjon",
        "i",
        "\u00e5rene",
        "\n",
        "VA",
        "Ine",
        "PE",
        "ag",
        "fra",
        "1825-1859.",
        "Og",
        "administrasjonen",
        "anvendte",
        "konsti-",
        "\n",
        "nome",
        "VE",
        "aksjonsformen",
        "ved",
        "opprettelsen",
        "av",
        "nye",
        "embeter",
        ",",
        "hvor",
        "\n",
        "V\u00c6R",
        "05",
        "fo",
        "\u00c5",
        "det",
        "alts\u00e5",
        "\u00e5penbart",
        "ikke",
        "kunne",
        "bli",
        "tale",
        "om",
        "noen",
        "\n",
        "fru",
        "p\u00e5",
        "a",
        "med",
        "Hestad",
        "midlertidig",
        "ledighet",
        ",",
        "fordi",
        "det",
        "aldri",
        "hadde",
        "eksi-",
        "\n",
        "Buan",
        "sluttet",
        ")",
        "stert",
        "noen",
        "annen",
        "fast",
        "innehaver",
        "hvis",
        "forhold",
        "dannet",
        "\n",
        "en",
        "konstitusjonsgrunn",
        ".",
        "Meningen",
        "med",
        "disse",
        "stil-",
        "\n",
        "lingers",
        "besettelse",
        "var",
        "da",
        "ogs\u00e5",
        "at",
        "den",
        "konstituerte",
        "\n",
        "skulle",
        "bli",
        "i",
        "embetet",
        ",",
        "men",
        "med",
        "l\u00e5n",
        "bevisste",
        "forut-",
        "\n",
        "setning",
        "fra",
        "administrasjonens",
        "side",
        "at",
        "den",
        "skulle",
        "\n",
        "kunne",
        "foreta",
        "omreguleringer",
        "av",
        "embetet",
        ",",
        "helt",
        "ned-",
        "\n",
        "legge",
        "det",
        "og",
        "endog",
        "oppsi",
        "eller",
        "avsette",
        "innehaveren",
        "\n",
        "uten",
        "\u00e5",
        "nedlegge",
        "embetet",
        ".",
        "Videre",
        "opplyser",
        "Helliksen",
        "\n",
        "mens",
        "Stortinget",
        "1",
        "nyere",
        "tid",
        "\n",
        "at",
        "mkxfensridirsidkesteiodyitte",
        "hadde",
        "vist",
        "sin",
        "vel",
        "\n",
        "i",
        "vilje",
        "overfor",
        "konstitusjonsreformen",
        "ved",
        "uttrykkelig",
        "\u00e5",
        "\n",
        "gi",
        "mw",
        "anvisning",
        "derp\u00e5",
        "(",
        "eks",
        ".",
        "stortingsdokument",
        "nr.70-",
        "\n",
        "1911",
        "8.",
        "1",
        ")",
        ",",
        "nader",
        "tidligere",
        "gjentatte",
        "ganger",
        "mis-",
        "\n",
        "billiget",
        "den",
        "uegentlige",
        "konstitusjon",
        ".",
        "protokoll-",
        "\n",
        "komiteen",
        "i",
        "1839",
        "uttalte",
        "at",
        "slik",
        "konstitusjon",
        "p\u00e5",
        "an-",
        "\n",
        "ses",
        "som",
        "en",
        "virkelig",
        "fast",
        "ansettelse",
        ",",
        "slik",
        "at",
        "deslige",
        "\n",
        "for",
        "\u00f8n",
        "Mands",
        "hele",
        "embedstid",
        "bestemte",
        "Konstitutionen",
        "\n",
        "ikke",
        "skj\u00f8nnes",
        "\u00e5",
        "v\u00e6re",
        "forfatningsmessige",
        "og",
        "\"",
        "saavel",
        "\u00c5",
        "\n",
        "'",
        "med",
        "Hensyn",
        "til",
        "Varighet",
        "av",
        "Postens",
        "Besiddelse",
        "som",
        "\u00c5",
        "\n",
        "adgangen",
        "til",
        "Pension",
        "har",
        "v\u00e6ret",
        "betragtet",
        "1",
        "lige",
        ";",
        "\n"
    ],
    "lemmatized_tokens": [
        "AE",
        "le",
        "$.",
        "\n",
        "ae",
        "f\u00f6re",
        "konstitusjonell",
        "ansvar",
        "for",
        "Regjeringen",
        "$(",
        "Rt",
        "$.",
        "\n",
        "$;",
        "$'",
        "1918",
        "s.",
        "646",
        "$)",
        "$\"",
        "$,",
        "\n",
        "I",
        "Bt",
        "$.",
        "1915",
        "5.753-761",
        "v\u00e6re",
        "det",
        "en",
        "artikkel",
        "av",
        "\n",
        "overrettssakf\u00f8rer",
        "Sverre",
        "Helliksen",
        "$:",
        "kunne",
        "en",
        "konsti-",
        "\n",
        "g.",
        "tvert",
        "embedsmand",
        "avsette",
        "uten",
        "dom",
        "?\"",
        "$.",
        "artikkel",
        "\n",
        "inneholde",
        "bla",
        "historisk",
        "opplysning",
        "om",
        "konstl-",
        "\n",
        "tusjonsform",
        "benyttelse",
        "$.",
        "s\u00e5ledes",
        "v\u00e6re",
        "regjerings-",
        "\n",
        "|advokatembet",
        "bare",
        "besa",
        "ved",
        "konstitusjon",
        "i",
        "\u00e5r",
        "\n",
        "VA",
        "Ine",
        "PE",
        "ag",
        "fra",
        "1825-1859.",
        "og",
        "administrasjon",
        "anvende",
        "konsti-",
        "\n",
        "nome",
        "VE",
        "aksjonsform",
        "ved",
        "opprettelse",
        "av",
        "ny",
        "embete",
        "$,",
        "hvor",
        "\n",
        "V\u00c6R",
        "05",
        "fo",
        "\u00e5",
        "det",
        "alts\u00e5",
        "\u00e5penbar",
        "ikke",
        "kunne",
        "bli",
        "tale",
        "om",
        "noen",
        "\n",
        "fru",
        "p\u00e5",
        "a",
        "med",
        "Hestad",
        "midlertidig",
        "ledighet",
        "$,",
        "fordi",
        "det",
        "aldri",
        "ha",
        "eksi-",
        "\n",
        "Buan",
        "slutte",
        "$)",
        "stere",
        "noen",
        "annen",
        "fast",
        "innehaver",
        "hvis",
        "forhold",
        "danne",
        "\n",
        "en",
        "konstitusjonsgrunn",
        "$.",
        "mening",
        "med",
        "disse",
        "stil-",
        "\n",
        "lingers",
        "besettelse",
        "v\u00e6re",
        "da",
        "ogs\u00e5",
        "at",
        "den",
        "konstituere",
        "\n",
        "skulle",
        "bli",
        "i",
        "embet",
        "$,",
        "men",
        "med",
        "l\u00e5n",
        "bevisst",
        "forut-",
        "\n",
        "setning",
        "fra",
        "administrasjon",
        "side",
        "at",
        "den",
        "skulle",
        "\n",
        "kunne",
        "foreta",
        "omregulering",
        "av",
        "embet",
        "$,",
        "hel",
        "ned-",
        "\n",
        "legge",
        "det",
        "og",
        "endog",
        "oppsi",
        "eller",
        "avsette",
        "innehaver",
        "\n",
        "uten",
        "\u00e5",
        "nedlegge",
        "embet",
        "$.",
        "vid",
        "opplyse",
        "Helliksen",
        "\n",
        "mens",
        "Stortinget",
        "1",
        "ny",
        "tid",
        "\n",
        "at",
        "mkxfensridirsidkesteiodyitte",
        "ha",
        "vise",
        "sin",
        "vel",
        "\n",
        "i",
        "vilje",
        "overfor",
        "konstitusjonsreform",
        "ved",
        "uttrykkelig",
        "\u00e5",
        "\n",
        "gi",
        "mw",
        "anvisning",
        "derp\u00e5",
        "$(",
        "eks",
        "$.",
        "stortingsdokument",
        "nr.70-",
        "\n",
        "1911",
        "8.",
        "1",
        "$)",
        "$,",
        "nade",
        "tidlig",
        "gjenta",
        "gang",
        "mis-",
        "\n",
        "billig",
        "den",
        "uegentlig",
        "konstitusjon",
        "$.",
        "protokoll-",
        "\n",
        "komit\u00e9",
        "i",
        "1839",
        "uttale",
        "at",
        "slik",
        "konstitusjon",
        "p\u00e5",
        "an-",
        "\n",
        "ses",
        "som",
        "en",
        "virkelig",
        "fast",
        "ansettelse",
        "$,",
        "slik",
        "at",
        "deslig",
        "\n",
        "for",
        "\u00f8n",
        "Mand",
        "hel",
        "embedstid",
        "bestemme",
        "Konstitutionen",
        "\n",
        "ikke",
        "skj\u00f8nne",
        "\u00e5",
        "v\u00e6re",
        "forfatningsmessig",
        "og",
        "$\"",
        "saavel",
        "\u00e5",
        "\n",
        "$\"",
        "med",
        "Hensyn",
        "til",
        "Varighet",
        "av",
        "Posten",
        "Besiddelse",
        "som",
        "\u00e5",
        "\n",
        "adgang",
        "til",
        "Pension",
        "ha",
        "v\u00e6r",
        "betragte",
        "1",
        "lig",
        "$;",
        "\n"
    ]
}