{
    "urnid": "db60044923000363",
    "img_path": "./images/db60044923000363.jpg",
    "raw_ocr_text": "| q\ni Mk ma amaer butte. Ha \u00c5rendam Var\nWal h\u00f8r komme Ad minute et sm Avilg un,\nGut beder inidlnts\n- ken Men huler Milk Gr, Ar efndkett bar\nE Ba lanisappreglinmamlaks \u00a3 1: Mannmede het\nAE Ar \u00c5 ni ap ramset al Amilik viden olyrs\n% | ver amme as data rd eds venns PG\n| M\u00f8ker mad paa N\u00c5L pars aplsltude at di!\ntukte rulkak vw \u00c5 MA ard hun lg missa\nmA milk minut mi ds qyum af\n| ' m\u00f8dtelufr kap dm hor mg. NE\nMAL av \u00c5R! bm BuamiaapnalmudF \u00e5t\n\u00e5 \u00e5 mmmmmde aan mildt inmmbild. \u00c5 hdd!\n| nidkake Mam Va ride at st m\u00e5dtak i kle kan\nkall mud GE en AA\nEr Ve hl oe dte Fs pg\nE vmillarkide oppatdr hvil velg\norde drep UG UR aover\u2014vker\nik hird h\u00f8nok At-eitanlele drink\n| vedek\u00f8ober Alike \u00e5 P\n| medarbeider om dar -\ni kg tu av mr At humaprrtp me jov\n0 am fre Adel sak \u00e5 hatt tag mkkale.\n| om n\u00e5r Raika m\u00e5 namneafe mislitr Melen Meat aplde\n| \u00c5ow brlandlingn ar Mr ppm 189.\n",
    "corrected_ocr_text": "i q\ni Mk ma amper butte. Ha Arendal Var\nWal h\u00f8r komme Ad minute et sm Avila un,\nGut beder incidents\n- ken Men huler Milk Gr, Ar efndkett bar\nE Ba lanisappreglinmamlaks i 1: dannede het\nAE Ar \u00c5 ni ap ramset al Amilie viden lys\n% i ver amme as data rd eds venns PG\ni \u00f8ker mad paa NHL pars aplsltude at di!\ntukte vulkan vw \u00c5 MA ard hun lg missa\nmA milk minut mi ds \u00d8yum af\ni ' m\u00f8dtelufr kap dm hor mg. NE\nMAL av \u00c5R! bm BuamiaapnalmudF \u00e5t\n\u00e5 \u00e5 mmmmm aan mildt innbild. \u00c5 Odd!\ni nikke Mam Va ride at st medtak i kle kan\nkall mud GE en AA\nEr Ve hl oe dte Fs pg\nE vmillarkide oppst\u00e5r hvil velg\norde drep UG UR aover\u2014vker\nik hird nok At-eitanlele drink\ni vedek\u00f8ober Alike \u00e5 P\ni medarbeider om dar -\ni kg tu av mr At humaprrtp me jov\n0 am fre Adel sak \u00e5 hatt tag lokale.\ni om n\u00e5r Raisa m\u00e5 namneafe milit\u00e6r Melen Meat alde\ni Dow brlandlingn ar Mr ppm 189.\n",
    "tokens": [
        "i",
        "q",
        "\n",
        "i",
        "Mk",
        "ma",
        "amper",
        "butte",
        ".",
        "Ha",
        "Arendal",
        "Var",
        "\n",
        "Wal",
        "h\u00f8r",
        "komme",
        "Ad",
        "minute",
        "et",
        "sm",
        "Avila",
        "un",
        ",",
        "\n",
        "Gut",
        "beder",
        "incidents",
        "\n",
        "-",
        "ken",
        "Men",
        "huler",
        "Milk",
        "Gr",
        ",",
        "Ar",
        "efndkett",
        "bar",
        "\n",
        "E",
        "Ba",
        "lanisappreglinmamlaks",
        "i",
        "1",
        ":",
        "dannede",
        "het",
        "\n",
        "AE",
        "Ar",
        "\u00c5",
        "ni",
        "ap",
        "ramset",
        "al",
        "Amilie",
        "viden",
        "lys",
        "\n",
        "%",
        "i",
        "ver",
        "amme",
        "as",
        "data",
        "rd",
        "eds",
        "venns",
        "PG",
        "\n",
        "i",
        "\u00f8ker",
        "mad",
        "paa",
        "NHL",
        "pars",
        "aplsltude",
        "at",
        "di",
        "!",
        "\n",
        "tukte",
        "vulkan",
        "vw",
        "\u00c5",
        "MA",
        "ard",
        "hun",
        "lg",
        "missa",
        "\n",
        "mA",
        "milk",
        "minut",
        "mi",
        "ds",
        "\u00d8yum",
        "af",
        "\n",
        "i",
        "'",
        "m\u00f8dtelufr",
        "kap",
        "dm",
        "hor",
        "mg",
        ".",
        "NE",
        "\n",
        "MAL",
        "av",
        "\u00c5R",
        "!",
        "bm",
        "BuamiaapnalmudF",
        "\u00e5t",
        "\n",
        "\u00e5",
        "\u00e5",
        "mmmmm",
        "aan",
        "mildt",
        "innbild",
        ".",
        "\u00c5",
        "Odd",
        "!",
        "\n",
        "i",
        "nikke",
        "Mam",
        "Va",
        "ride",
        "at",
        "st",
        "medtak",
        "i",
        "kle",
        "kan",
        "\n",
        "kall",
        "mud",
        "GE",
        "en",
        "AA",
        "\n",
        "Er",
        "Ve",
        "hl",
        "oe",
        "dte",
        "Fs",
        "pg",
        "\n",
        "E",
        "vmillarkide",
        "oppst\u00e5r",
        "hvil",
        "velg",
        "\n",
        "orde",
        "drep",
        "UG",
        "UR",
        "aover\u2014vker",
        "\n",
        "ik",
        "hird",
        "nok",
        "At-eitanlele",
        "drink",
        "\n",
        "i",
        "vedek\u00f8ober",
        "Alike",
        "\u00e5",
        "P",
        "\n",
        "i",
        "medarbeider",
        "om",
        "dar",
        "-",
        "\n",
        "i",
        "kg",
        "tu",
        "av",
        "mr",
        "At",
        "humaprrtp",
        "me",
        "jov",
        "\n",
        "0",
        "am",
        "fre",
        "Adel",
        "sak",
        "\u00e5",
        "hatt",
        "tag",
        "lokale",
        ".",
        "\n",
        "i",
        "om",
        "n\u00e5r",
        "Raisa",
        "m\u00e5",
        "namneafe",
        "milit\u00e6r",
        "Melen",
        "Meat",
        "alde",
        "\n",
        "i",
        "Dow",
        "brlandlingn",
        "ar",
        "Mr",
        "ppm",
        "189.",
        "\n"
    ],
    "lemmatized_tokens": [
        "i",
        "q",
        "\n",
        "i",
        "Mk",
        "ma",
        "ampe",
        "butte",
        "$.",
        "ha",
        "Arendal",
        "v\u00e6re",
        "\n",
        "Wal",
        "h\u00f8r",
        "komme",
        "Ad",
        "minute",
        "en",
        "sm",
        "Avila",
        "un",
        "$,",
        "\n",
        "Gut",
        "beder",
        "Incidents",
        "\n",
        "$-",
        "ken",
        "men",
        "huler",
        "Milk",
        "Gr",
        "$,",
        "Ar",
        "efndkett",
        "b\u00e6re",
        "\n",
        "E",
        "Ba",
        "lanisappreglinmamlaks",
        "i",
        "1",
        "$:",
        "danned",
        "hete",
        "\n",
        "AE",
        "Ar",
        "\u00e5",
        "ni",
        "Ap",
        "ramse",
        "al",
        "Amilie",
        "vide",
        "lys",
        "\n",
        "%",
        "i",
        "ver",
        "amme",
        "as",
        "data",
        "rd",
        "eds",
        "venn",
        "PG",
        "\n",
        "i",
        "\u00f8ke",
        "Mad",
        "paa",
        "NHL",
        "par",
        "aplsltude",
        "at",
        "din",
        "$!",
        "\n",
        "tukte",
        "vulkan",
        "vw",
        "\u00e5",
        "MA",
        "ard",
        "hun",
        "lg",
        "missa",
        "\n",
        "mA",
        "milk",
        "minut",
        "min",
        "ds.",
        "\u00d8yum",
        "af",
        "\n",
        "i",
        "$'",
        "m\u00f8dtelufr",
        "kap",
        "dm",
        "hor",
        "mg",
        "$.",
        "NE",
        "\n",
        "MAL",
        "av",
        "\u00c5R",
        "$!",
        "bm",
        "BuamiaapnalmudF",
        "\u00e5t",
        "\n",
        "\u00e5",
        "\u00e5",
        "mmmmm",
        "aan",
        "mild",
        "innbild",
        "$.",
        "\u00e5",
        "Odd",
        "$!",
        "\n",
        "i",
        "nikke",
        "Mam",
        "Va",
        "ride",
        "at",
        "st.",
        "medtak",
        "i",
        "kle",
        "kunne",
        "\n",
        "kall",
        "mud",
        "GE",
        "en",
        "AA",
        "\n",
        "v\u00e6re",
        "Ve",
        "hl",
        "oe",
        "dte",
        "Fs",
        "pg",
        "\n",
        "E",
        "vmillarkide",
        "oppst\u00e5",
        "hvil",
        "velge",
        "\n",
        "orde",
        "drep",
        "UG",
        "UR",
        "aover\u2014vk",
        "\n",
        "ik",
        "hird",
        "nok",
        "At-eitanlele",
        "drink",
        "\n",
        "i",
        "vedek\u00f8ober",
        "Alike",
        "\u00e5",
        "P",
        "\n",
        "i",
        "medarbeider",
        "om",
        "dar",
        "$-",
        "\n",
        "i",
        "kg",
        "tu",
        "av",
        "mr",
        "at",
        "humaprrtp",
        "me",
        "jov",
        "\n",
        "0",
        "am",
        "fre",
        "Adel",
        "sak",
        "\u00e5",
        "ha",
        "tag",
        "lokal",
        "$.",
        "\n",
        "i",
        "om",
        "n\u00e5r",
        "Raisa",
        "m\u00e5tte",
        "namneafe",
        "milit\u00e6r",
        "Melen",
        "Meat",
        "alde",
        "\n",
        "i",
        "Dow",
        "brlandling",
        "ar",
        "Mr",
        "ppm",
        "189.",
        "\n"
    ]
}