{
    "urnid": "db60044923000520",
    "img_path": "./images/db60044923000520.jpg",
    "raw_ocr_text": "RE\nFAE Em\namet vanket vanttetng \u00e5 GOmtlagen; Det ble o\u00c5G from p\u00e5\nende Made vteterdd, vrenger 196006\n\u00e5 deg ot Gptte, p\u00e5 samt nkte son foebausldet 4 tklNnrvntng HLL. i\nlaget\u00bb myndighet otter pil. \u00e575 4, Dan det Aadee vare meon id\nS\u00e5 Sr ' skjer Agnar \u00c9 og ogentiige penn Joner. I \u00e5 E\nEeg homeyn 41 pooksts \u00e5 olkee 06 han for Orig honvinfe\n0 ete Meterte \u00f8tt\u00f8r 10149) om or voblagg 00). 4en d\u00f8ptale por\u00bb\n",
    "corrected_ocr_text": "RE\nFAE Em\ngamet vanket vanttetng \u00e5 GOmtlagen; Det ble H\u00c5G from p\u00e5\nende Made vteterdd, vrenger 196006\n\u00e5 deg ot Gitte, p\u00e5 samt \u00f8kte son foebausldet 4 tklNnrvntng LHL. i\nlaget myndighet otter pil. \u00e575 4, Dan det Aadne vare men id\nS\u00e5 Sr ' skjer Agnar \u00c9 og egentlige penn Joner. I \u00e5 E\nEeg homeyz 41 pockets \u00e5 olje 06 han for krig honvinfe\n0 ete feterte etter 10149) om or volang 00). 4en d\u00f8pte port\n",
    "tokens": [
        "RE",
        "\n",
        "FAE",
        "Em",
        "\n",
        "gamet",
        "vanket",
        "vanttetng",
        "\u00e5",
        "GOmtlagen;",
        "Det",
        "ble",
        "H\u00c5G",
        "from",
        "p\u00e5",
        "\n",
        "ende",
        "Made",
        "vteterdd",
        ",",
        "vrenger",
        "196006",
        "\n",
        "\u00e5",
        "deg",
        "ot",
        "Gitte",
        ",",
        "p\u00e5",
        "samt",
        "\u00f8kte",
        "son",
        "foebausldet",
        "4",
        "tklNnrvntng",
        "LHL",
        ".",
        "i",
        "\n",
        "laget",
        "myndighet",
        "otter",
        "pil",
        ".",
        "\u00e575",
        "4",
        ",",
        "Dan",
        "det",
        "Aadne",
        "vare",
        "men",
        "id",
        "\n",
        "S\u00e5",
        "Sr",
        "'",
        "skjer",
        "Agnar",
        "\u00c9",
        "og",
        "egentlige",
        "penn",
        "Joner",
        ".",
        "I",
        "\u00e5",
        "E",
        "\n",
        "Eeg",
        "homeyz",
        "41",
        "pockets",
        "\u00e5",
        "olje",
        "06",
        "han",
        "for",
        "krig",
        "honvinfe",
        "\n",
        "0",
        "ete",
        "feterte",
        "etter",
        "10149",
        ")",
        "om",
        "or",
        "volang",
        "00",
        ")",
        ".",
        "4en",
        "d\u00f8pte",
        "port",
        "\n"
    ],
    "lemmatized_tokens": [
        "RE",
        "\n",
        "FAE",
        "Em",
        "\n",
        "gamet",
        "vanke",
        "vanttetng",
        "\u00e5",
        "GOmtlagen;",
        "det",
        "bli",
        "H\u00c5G",
        "from",
        "p\u00e5",
        "\n",
        "ende",
        "Made",
        "vteterdd",
        "$,",
        "vrenge",
        "196006",
        "\n",
        "\u00e5",
        "du",
        "ot",
        "Gitte",
        "$,",
        "p\u00e5",
        "samt",
        "\u00f8ke",
        "son",
        "foebauslde",
        "4",
        "tklNnrvntng",
        "LHL",
        "$.",
        "i",
        "\n",
        "lag",
        "myndighet",
        "otte",
        "pil",
        "$.",
        "\u00e575",
        "4",
        "$,",
        "Dan",
        "det",
        "Aadne",
        "vare",
        "men",
        "id.",
        "\n",
        "s\u00e5",
        "Sr",
        "$\"",
        "skje",
        "Agnar",
        "\u00c9",
        "og",
        "egentlig",
        "penn",
        "Joner",
        "$.",
        "i",
        "\u00e5",
        "E",
        "\n",
        "Eeg",
        "homeyz",
        "41",
        "pockets",
        "\u00e5",
        "olje",
        "06",
        "han",
        "for",
        "krig",
        "honvinfe",
        "\n",
        "0",
        "ete",
        "fetere",
        "etter",
        "10149",
        "$)",
        "om",
        "or",
        "volang",
        "00",
        "$)",
        "$.",
        "4en",
        "d\u00f8pe",
        "port",
        "\n"
    ]
}